Metadata-Version: 2.4
Name: githydra
Version: 3.1.0
Summary: Comprehensive Git Automation CLI Tool with Beautiful Terminal UI and Template Management
Home-page: https://github.com/Alqudimi/GitHydra
Author: Abdulaziz Alqudimi
Author-email: eng7mi@gmail.com
License: MIT
Project-URL: Bug Reports, https://github.com/Alqudimi/GitHydra/issues
Project-URL: Source, https://github.com/Alqudimi/GitHydra
Project-URL: Documentation, https://github.com/Alqudimi/GitHydra/tree/main/docs
Project-URL: Changelog, https://github.com/Alqudimi/GitHydra/releases
Keywords: git,cli,automation,terminal,ui,version-control,developer-tools,productivity,templates,project-management,collaboration,command-line,rich,github,gitlab
Platform: any
Classifier: Development Status :: 5 - Production/Stable
Classifier: Intended Audience :: Developers
Classifier: Intended Audience :: System Administrators
Classifier: Intended Audience :: Information Technology
Classifier: Topic :: Software Development :: Version Control :: Git
Classifier: Topic :: Software Development :: User Interfaces
Classifier: Topic :: Software Development :: Libraries :: Python Modules
Classifier: Topic :: System :: Shells
Classifier: Topic :: Terminals
Classifier: Topic :: Utilities
Classifier: License :: OSI Approved :: MIT License
Classifier: Programming Language :: Python :: 3
Classifier: Programming Language :: Python :: 3.8
Classifier: Programming Language :: Python :: 3.9
Classifier: Programming Language :: Python :: 3.10
Classifier: Programming Language :: Python :: 3.11
Classifier: Programming Language :: Python :: 3.12
Classifier: Operating System :: OS Independent
Classifier: Operating System :: Microsoft :: Windows
Classifier: Operating System :: POSIX
Classifier: Operating System :: Unix
Classifier: Operating System :: MacOS
Classifier: Environment :: Console
Classifier: Environment :: Console :: Curses
Classifier: Natural Language :: English
Classifier: Natural Language :: Arabic
Classifier: Framework :: AsyncIO
Classifier: Framework :: Buildout
Requires-Python: >=3.8
License-File: LICENSE
Requires-Dist: click>=8.1.0
Requires-Dist: colorama>=0.4.6
Requires-Dist: gitpython>=3.1.40
Requires-Dist: pyyaml>=6.0
Requires-Dist: questionary>=2.0.0
Requires-Dist: rich>=13.7.0
Requires-Dist: pygithub>=2.8.0
Requires-Dist: tqdm>=4.65.0
Dynamic: author
Dynamic: author-email
Dynamic: classifier
Dynamic: description
Dynamic: description-content-type
Dynamic: home-page
Dynamic: keywords
Dynamic: license
Dynamic: license-file
Dynamic: platform
Dynamic: project-url
Dynamic: requires-dist
Dynamic: requires-python
Dynamic: summary
